{
  "hash": "cf461d5f",
  "configHash": "2f407944",
  "lockfileHash": "1a38fc36",
  "browserHash": "b8b42de4",
  "optimized": {
    "vue": {
      "src": "../../../../node_modules/vue/dist/vue.runtime.esm-bundler.js",
      "file": "vue.js",
      "fileHash": "81f62838",
      "needsInterop": false
    },
    "vitepress > @vue/devtools-api": {
      "src": "../../../../node_modules/@vue/devtools-api/dist/index.js",
      "file": "vitepress___@vue_devtools-api.js",
      "fileHash": "f7401d39",
      "needsInterop": false
    },
    "vitepress > @vueuse/core": {
      "src": "../../../../node_modules/@vueuse/core/index.mjs",
      "file": "vitepress___@vueuse_core.js",
      "fileHash": "251e96c2",
      "needsInterop": false
    },
    "vitepress > @vueuse/integrations/useFocusTrap": {
      "src": "../../../../node_modules/@vueuse/integrations/useFocusTrap.mjs",
      "file": "vitepress___@vueuse_integrations_useFocusTrap.js",
      "fileHash": "4fcff903",
      "needsInterop": false
    },
    "vitepress > mark.js/src/vanilla.js": {
      "src": "../../../../node_modules/mark.js/src/vanilla.js",
      "file": "vitepress___mark__js_src_vanilla__js.js",
      "fileHash": "3478fa8a",
      "needsInterop": false
    },
    "vitepress > minisearch": {
      "src": "../../../../node_modules/minisearch/dist/es/index.js",
      "file": "vitepress___minisearch.js",
      "fileHash": "927d9302",
      "needsInterop": false
    }
  },
  "chunks": {
    "chunk-GD2PZ323": {
      "file": "chunk-GD2PZ323.js"
    },
    "chunk-LW4I4DCF": {
      "file": "chunk-LW4I4DCF.js"
    }
  }
}